{
    "date_published": "2026-03-02",
    "markets": [
        {
            "data_month": "2025-07-01",
            "inquiry_month": "2025-11-01",
            "inquiry_yoy_change": "2.5% decrease",
            "market_key": "AUT",
            "num_originations": "2.3 million",
            "tightness_month": "2025-09-01",
            "tightness_yoy_change": "3.5% decrease",
            "value_originations": "$70.2 billion",
            "year_over_year_change": "2.7% increase"
        },
        {
            "data_month": "2025-07-01",
            "inquiry_month": "2025-11-01",
            "inquiry_yoy_change": "1.8% decrease",
            "market_key": "CRC",
            "num_originations": "8.3 million",
            "tightness_month": "2025-09-01",
            "tightness_yoy_change": "0.2% decrease",
            "value_originations": "$45.2 billion",
            "year_over_year_change": "14.0% increase"
        },
        {
            "data_month": "2025-07-01",
            "inquiry_month": "2025-11-01",
            "inquiry_yoy_change": "1.7% decrease",
            "market_key": "MTG",
            "num_originations": "432,063",
            "tightness_month": "2025-08-01",
            "tightness_yoy_change": "3.1% increase",
            "value_originations": "$159.2 billion",
            "year_over_year_change": "1.3% increase"
        },
        {
            "data_month": "2025-07-01",
            "market_key": "STU",
            "num_originations": "809,927",
            "value_originations": "$13.3 billion",
            "year_over_year_change": "4.2% increase"
        }
    ]
}