{
    "date_published": "2025-05-15",
    "markets": [
        {
            "data_month": "2024-10-01",
            "inquiry_month": "2025-02-01",
            "inquiry_yoy_change": "17.8% decrease",
            "market_key": "CRC",
            "num_originations": "6.9 million",
            "tightness_month": "2024-12-01",
            "tightness_yoy_change": "3.0% decrease",
            "value_originations": "$39.3 billion",
            "year_over_year_change": "1.3% increase"
        },
        {
            "data_month": "2024-10-01",
            "market_key": "STU",
            "num_originations": "1.2 million",
            "value_originations": "$9.6 billion",
            "year_over_year_change": "0.9% decrease"
        },
        {
            "data_month": "2024-10-01",
            "inquiry_month": "2025-02-01",
            "inquiry_yoy_change": "3.9% decrease",
            "market_key": "AUT",
            "num_originations": "2.1 million",
            "tightness_month": "2024-12-01",
            "tightness_yoy_change": "4.4% decrease",
            "value_originations": "$63.1 billion",
            "year_over_year_change": "8.4% increase"
        },
        {
            "data_month": "2024-10-01",
            "inquiry_month": "2025-02-01",
            "inquiry_yoy_change": "16.0% decrease",
            "market_key": "MTG",
            "num_originations": "462,902",
            "tightness_month": "2024-11-01",
            "tightness_yoy_change": "4.2% increase",
            "value_originations": "$171.0 billion",
            "year_over_year_change": "36.8% increase"
        }
    ]
}