[
    {
        "name": "AL",
        "value": "31.67"
    },
    {
        "name": "AK",
        "value": "-72.93"
    },
    {
        "name": "AZ",
        "value": "-37.57"
    },
    {
        "name": "AR",
        "value": "118.37"
    },
    {
        "name": "CA",
        "value": "18.80"
    },
    {
        "name": "CO",
        "value": "-24.38"
    },
    {
        "name": "CT",
        "value": "-20.79"
    },
    {
        "name": "DE",
        "value": "27.31"
    },
    {
        "name": "DC",
        "value": "122.67"
    },
    {
        "name": "FL",
        "value": "-28.77"
    },
    {
        "name": "GA",
        "value": "32.97"
    },
    {
        "name": "HI",
        "value": "47.15"
    },
    {
        "name": "ID",
        "value": "-37.74"
    },
    {
        "name": "IL",
        "value": "25.18"
    },
    {
        "name": "IN",
        "value": "-1.67"
    },
    {
        "name": "IA",
        "value": "1.99"
    },
    {
        "name": "KS",
        "value": "35.89"
    },
    {
        "name": "KY",
        "value": "51.76"
    },
    {
        "name": "LA",
        "value": "-9.18"
    },
    {
        "name": "ME",
        "value": "55.73"
    },
    {
        "name": "MD",
        "value": "15.60"
    },
    {
        "name": "MA",
        "value": "-1.80"
    },
    {
        "name": "MI",
        "value": "-13.64"
    },
    {
        "name": "MN",
        "value": "29.54"
    },
    {
        "name": "MS",
        "value": "-1.29"
    },
    {
        "name": "MO",
        "value": "1.93"
    },
    {
        "name": "MT",
        "value": "10.14"
    },
    {
        "name": "NE",
        "value": "-2.95"
    },
    {
        "name": "NV",
        "value": "20.20"
    },
    {
        "name": "NH",
        "value": "25.36"
    },
    {
        "name": "NJ",
        "value": "4.84"
    },
    {
        "name": "NM",
        "value": "26.15"
    },
    {
        "name": "NY",
        "value": "5.52"
    },
    {
        "name": "NC",
        "value": "57.29"
    },
    {
        "name": "ND",
        "value": "56.05"
    },
    {
        "name": "OH",
        "value": "-9.86"
    },
    {
        "name": "OK",
        "value": "46.64"
    },
    {
        "name": "OR",
        "value": "35.65"
    },
    {
        "name": "PA",
        "value": "9.08"
    },
    {
        "name": "RI",
        "value": "-3.28"
    },
    {
        "name": "SC",
        "value": "10.42"
    },
    {
        "name": "SD",
        "value": "-54.02"
    },
    {
        "name": "TN",
        "value": "6.17"
    },
    {
        "name": "TX",
        "value": "-5.18"
    },
    {
        "name": "UT",
        "value": "31.71"
    },
    {
        "name": "VT",
        "value": "-2.82"
    },
    {
        "name": "VA",
        "value": "-22.72"
    },
    {
        "name": "WA",
        "value": "-23.44"
    },
    {
        "name": "WV",
        "value": "95.64"
    },
    {
        "name": "WI",
        "value": "5.21"
    },
    {
        "name": "WY",
        "value": "-29.56"
    }
]