[
    {
        "name": "AL",
        "value": "-56.44"
    },
    {
        "name": "AK",
        "value": "43.81"
    },
    {
        "name": "AZ",
        "value": "-54.94"
    },
    {
        "name": "AR",
        "value": "-22.65"
    },
    {
        "name": "CA",
        "value": "-33.15"
    },
    {
        "name": "CO",
        "value": "-47.84"
    },
    {
        "name": "CT",
        "value": "-28.70"
    },
    {
        "name": "DE",
        "value": "-40.18"
    },
    {
        "name": "DC",
        "value": "-45.05"
    },
    {
        "name": "FL",
        "value": "-51.46"
    },
    {
        "name": "GA",
        "value": "-56.98"
    },
    {
        "name": "HI",
        "value": "-53.41"
    },
    {
        "name": "ID",
        "value": "-56.53"
    },
    {
        "name": "IL",
        "value": "-50.14"
    },
    {
        "name": "IN",
        "value": "-37.21"
    },
    {
        "name": "IA",
        "value": "-35.62"
    },
    {
        "name": "KS",
        "value": "-42.86"
    },
    {
        "name": "KY",
        "value": "-48.92"
    },
    {
        "name": "LA",
        "value": "-17.79"
    },
    {
        "name": "ME",
        "value": "-35.80"
    },
    {
        "name": "MD",
        "value": "-25.75"
    },
    {
        "name": "MA",
        "value": "-33.12"
    },
    {
        "name": "MI",
        "value": "-40.71"
    },
    {
        "name": "MN",
        "value": "-44.33"
    },
    {
        "name": "MS",
        "value": "-14.11"
    },
    {
        "name": "MO",
        "value": "-46.89"
    },
    {
        "name": "MT",
        "value": "-7.52"
    },
    {
        "name": "NE",
        "value": "-64.23"
    },
    {
        "name": "NV",
        "value": "-43.19"
    },
    {
        "name": "NH",
        "value": "5.44"
    },
    {
        "name": "NJ",
        "value": "-20.09"
    },
    {
        "name": "NM",
        "value": "-60.01"
    },
    {
        "name": "NY",
        "value": "-34.47"
    },
    {
        "name": "NC",
        "value": "-59.36"
    },
    {
        "name": "ND",
        "value": "-61.12"
    },
    {
        "name": "OH",
        "value": "-42.08"
    },
    {
        "name": "OK",
        "value": "-39.39"
    },
    {
        "name": "OR",
        "value": "-24.35"
    },
    {
        "name": "PA",
        "value": "-42.82"
    },
    {
        "name": "RI",
        "value": "-10.16"
    },
    {
        "name": "SC",
        "value": "-46.20"
    },
    {
        "name": "SD",
        "value": "-22.39"
    },
    {
        "name": "TN",
        "value": "-58.73"
    },
    {
        "name": "TX",
        "value": "-49.68"
    },
    {
        "name": "UT",
        "value": "-41.49"
    },
    {
        "name": "VT",
        "value": "-58.30"
    },
    {
        "name": "VA",
        "value": "-23.58"
    },
    {
        "name": "WA",
        "value": "-39.60"
    },
    {
        "name": "WV",
        "value": "-24.05"
    },
    {
        "name": "WI",
        "value": "-42.28"
    },
    {
        "name": "WY",
        "value": "-1.64"
    }
]