[
    {
        "name": "AL",
        "value": "-14.34"
    },
    {
        "name": "AK",
        "value": "1.56"
    },
    {
        "name": "AZ",
        "value": "-9.25"
    },
    {
        "name": "AR",
        "value": "-8.18"
    },
    {
        "name": "CA",
        "value": "-3.26"
    },
    {
        "name": "CO",
        "value": "-5.05"
    },
    {
        "name": "CT",
        "value": "-0.22"
    },
    {
        "name": "DE",
        "value": "1.08"
    },
    {
        "name": "DC",
        "value": "-5.40"
    },
    {
        "name": "FL",
        "value": "-8.03"
    },
    {
        "name": "GA",
        "value": "-9.25"
    },
    {
        "name": "HI",
        "value": "11.85"
    },
    {
        "name": "ID",
        "value": "4.94"
    },
    {
        "name": "IL",
        "value": "-7.26"
    },
    {
        "name": "IN",
        "value": "-5.80"
    },
    {
        "name": "IA",
        "value": "-7.31"
    },
    {
        "name": "KS",
        "value": "-7.66"
    },
    {
        "name": "KY",
        "value": "-0.69"
    },
    {
        "name": "LA",
        "value": "-4.09"
    },
    {
        "name": "ME",
        "value": "-9.66"
    },
    {
        "name": "MD",
        "value": "1.63"
    },
    {
        "name": "MA",
        "value": "-2.96"
    },
    {
        "name": "MI",
        "value": "-1.09"
    },
    {
        "name": "MN",
        "value": "-7.76"
    },
    {
        "name": "MS",
        "value": "-3.12"
    },
    {
        "name": "MO",
        "value": "-7.53"
    },
    {
        "name": "MT",
        "value": "-5.77"
    },
    {
        "name": "NE",
        "value": "1.69"
    },
    {
        "name": "NV",
        "value": "-1.22"
    },
    {
        "name": "NH",
        "value": "3.44"
    },
    {
        "name": "NJ",
        "value": "-4.45"
    },
    {
        "name": "NM",
        "value": "-16.76"
    },
    {
        "name": "NY",
        "value": "-2.13"
    },
    {
        "name": "NC",
        "value": "-8.03"
    },
    {
        "name": "ND",
        "value": "-29.45"
    },
    {
        "name": "OH",
        "value": "-1.02"
    },
    {
        "name": "OK",
        "value": "7.18"
    },
    {
        "name": "OR",
        "value": "1.06"
    },
    {
        "name": "PA",
        "value": "-2.26"
    },
    {
        "name": "RI",
        "value": "-9.71"
    },
    {
        "name": "SC",
        "value": "-2.40"
    },
    {
        "name": "SD",
        "value": "-13.42"
    },
    {
        "name": "TN",
        "value": "-3.62"
    },
    {
        "name": "TX",
        "value": "-3.75"
    },
    {
        "name": "UT",
        "value": "-3.77"
    },
    {
        "name": "VT",
        "value": "-15.80"
    },
    {
        "name": "VA",
        "value": "-2.88"
    },
    {
        "name": "WA",
        "value": "-10.20"
    },
    {
        "name": "WV",
        "value": "3.12"
    },
    {
        "name": "WI",
        "value": "0.75"
    },
    {
        "name": "WY",
        "value": "-4.53"
    }
]